[
    {
        "id": "bitcoin",
        "symbol": "btc",
        "name": "Bitcoin",
        "image": "https://assets.coingecko.com/coins/images/1/large/bitcoin.png?1547033579",
        "current_price": 28917,
        "market_cap": 559451873230,
        "market_cap_rank": 1,
        "fully_diluted_valuation": 606647832408,
        "total_volume": 10509370564,
        "high_24h": 29430,
        "low_24h": 28485,
        "price_change_24h": -494.20729344123174,
        "price_change_percentage_24h": -1.68035,
        "market_cap_change_24h": -9802821609.063965,
        "market_cap_change_percentage_24h": -1.72204,
        "circulating_supply": 19366243.0,
        "total_supply": 21000000.0,
        "max_supply": 21000000.0,
        "ath": 69045,
        "ath_change_percentage": -58.16241,
        "ath_date": "2021-11-10T14:24:11.849Z",
        "atl": 67.81,
        "atl_change_percentage": 42500.0524,
        "atl_date": "2013-07-06T00:00:00.000Z",
        "roi": null,
        "last_updated": "2023-05-07T05:39:29.681Z"
    },
    {
        "id": "ethereum",
        "symbol": "eth",
        "name": "Ethereum",
        "image": "https://assets.coingecko.com/coins/images/279/large/ethereum.png?1595348880",
        "current_price": 1903.02,
        "market_cap": 228875461165,
        "market_cap_rank": 2,
        "fully_diluted_valuation": 228875461165,
        "total_volume": 10384078850,
        "high_24h": 1966.8,
        "low_24h": 1874.12,
        "price_change_24h": -63.244812720678965,
        "price_change_percentage_24h": -3.2165,
        "market_cap_change_24h": -7773037764.648163,
        "market_cap_change_percentage_24h": -3.28463,
        "circulating_supply": 120344574.703444,
        "total_supply": 120344574.703444,
        "max_supply": null,
        "ath": 4878.26,
        "ath_change_percentage": -61.09479,
        "ath_date": "2021-11-10T14:24:19.604Z",
        "atl": 0.432979,
        "atl_change_percentage": 438234.857,
        "atl_date": "2015-10-20T00:00:00.000Z",
        "roi": {
            "times": 86.98492498381013,
            "currency": "btc",
            "percentage": 8698.492498381012
        },
        "last_updated": "2023-05-07T05:39:25.696Z"
    },
    {
        "id": "tether",
        "symbol": "usdt",
        "name": "Tether",
        "image": "https://assets.coingecko.com/coins/images/325/large/Tether.png?1668148663",
        "current_price": 1.002,
        "market_cap": 82217029593,
        "market_cap_rank": 3,
        "fully_diluted_valuation": 82217029593,
        "total_volume": 23824961333,
        "high_24h": 1.013,
        "low_24h": 0.994068,
        "price_change_24h": 0.00108721,
        "price_change_percentage_24h": 0.1086,
        "market_cap_change_24h": 51513253,
        "market_cap_change_percentage_24h": 0.06269,
        "circulating_supply": 82078431886.1561,
        "total_supply": 82078431886.1561,
        "max_supply": null,
        "ath": 1.32,
        "ath_change_percentage": -24.32242,
        "ath_date": "2018-07-24T00:00:00.000Z",
        "atl": 0.572521,
        "atl_change_percentage": 74.89079,
        "atl_date": "2015-03-02T00:00:00.000Z",
        "roi": null,
        "last_updated": "2023-05-07T05:35:00.307Z"
    },
    {
        "id": "binancecoin",
        "symbol": "bnb",
        "name": "BNB",
        "image": "https://assets.coingecko.com/coins/images/825/large/bnb-icon2_2x.png?1644979850",
        "current_price": 323.52,
        "market_cap": 51091332349,
        "market_cap_rank": 4,
        "fully_diluted_valuation": 64719154000,
        "total_volume": 534440351,
        "high_24h": 325.98,
        "low_24h": 319.4,
        "price_change_24h": -2.2023842846250545,
        "price_change_percentage_24h": -0.67616,
        "market_cap_change_24h": -304887863.4301529,
        "market_cap_change_percentage_24h": -0.59321,
        "circulating_supply": 157886280.0,
        "total_supply": 157900174.0,
        "max_supply": 200000000.0,
        "ath": 686.31,
        "ath_change_percentage": -52.85979,
        "ath_date": "2021-05-10T07:24:17.097Z",
        "atl": 0.0398177,
        "atl_change_percentage": 812419.01447,
        "atl_date": "2017-10-19T00:00:00.000Z",
        "roi": null,
        "last_updated": "2023-05-07T05:39:32.341Z"
    },
    {
        "id": "usd-coin",
        "symbol": "usdc",
        "name": "USD Coin",
        "image": "https://assets.coingecko.com/coins/images/6319/large/USD_Coin_icon.png?1547042389",
        "current_price": 1.001,
        "market_cap": 30396707811,
        "market_cap_rank": 5,
        "fully_diluted_valuation": 30395813840,
        "total_volume": 4831630246,
        "high_24h": 1.01,
        "low_24h": 0.995372,
        "price_change_24h": 0.00088686,
        "price_change_percentage_24h": 0.0887,
        "market_cap_change_24h": 10897660,
        "market_cap_change_percentage_24h": 0.03586,
        "circulating_supply": 30394621809.477,
        "total_supply": 30393727899.477,
        "max_supply": null,
        "ath": 1.17,
        "ath_change_percentage": -14.74503,
        "ath_date": "2019-05-08T00:40:28.300Z",
        "atl": 0.877647,
        "atl_change_percentage": 13.91718,
        "atl_date": "2023-03-11T08:02:13.981Z",
        "roi": null,
        "last_updated": "2023-05-07T05:39:32.396Z"
    },
    {
        "id": "ripple",
        "symbol": "xrp",
        "name": "XRP",
        "image": "https://assets.coingecko.com/coins/images/44/large/xrp-symbol-white-128.png?1605778731",
        "current_price": 0.459515,
        "market_cap": 23788255009,
        "market_cap_rank": 6,
        "fully_diluted_valuation": 45889766926,
        "total_volume": 621742550,
        "high_24h": 0.465726,
        "low_24h": 0.453464,
        "price_change_24h": -0.005371090473511919,
        "price_change_percentage_24h": -1.15536,
        "market_cap_change_24h": -302147681.50769424,
        "market_cap_change_percentage_24h": -1.25422,
        "circulating_supply": 51837820505.0,
        "total_supply": 99988965239.0,
        "max_supply": 100000000000.0,
        "ath": 3.4,
        "ath_change_percentage": -86.50138,
        "ath_date": "2018-01-07T00:00:00.000Z",
        "atl": 0.00268621,
        "atl_change_percentage": 16977.7568,
        "atl_date": "2014-05-22T00:00:00.000Z",
        "roi": null,
        "last_updated": "2023-05-07T05:39:29.466Z"
    },
    {
        "id": "cardano",
        "symbol": "ada",
        "name": "Cardano",
        "image": "https://assets.coingecko.com/coins/images/975/large/cardano.png?1547034860",
        "current_price": 0.382,
        "market_cap": 13378805423,
        "market_cap_rank": 7,
        "fully_diluted_valuation": 17179223461,
        "total_volume": 251248761,
        "high_24h": 0.391011,
        "low_24h": 0.37561,
        "price_change_24h": -0.008467713436835557,
        "price_change_percentage_24h": -2.16861,
        "market_cap_change_24h": -298057110.3684788,
        "market_cap_change_percentage_24h": -2.17928,
        "circulating_supply": 35045020830.3234,
        "total_supply": 45000000000.0,
        "max_supply": 45000000000.0,
        "ath": 3.09,
        "ath_change_percentage": -87.63913,
        "ath_date": "2021-09-02T06:00:10.474Z",
        "atl": 0.01925275,
        "atl_change_percentage": 1881.89363,
        "atl_date": "2020-03-13T02:22:55.044Z",
        "roi": null,
        "last_updated": "2023-05-07T05:39:27.853Z"
    },
    {
        "id": "staked-ether",
        "symbol": "steth",
        "name": "Lido Staked Ether",
        "image": "https://assets.coingecko.com/coins/images/13442/large/steth_logo.png?1608607546",
        "current_price": 1899.95,
        "market_cap": 12009363041,
        "market_cap_rank": 8,
        "fully_diluted_valuation": 12009363041,
        "total_volume": 7658254,
        "high_24h": 1967.38,
        "low_24h": 1871.92,
        "price_change_24h": -62.927342205396144,
        "price_change_percentage_24h": -3.20588,
        "market_cap_change_24h": -381274086.97218513,
        "market_cap_change_percentage_24h": -3.07711,
        "circulating_supply": 6325978.60332239,
        "total_supply": 6325978.60332239,
        "max_supply": 6325978.60332239,
        "ath": 4829.57,
        "ath_change_percentage": -60.72009,
        "ath_date": "2021-11-10T14:40:47.256Z",
        "atl": 482.9,
        "atl_change_percentage": 292.84861,
        "atl_date": "2020-12-22T04:08:21.854Z",
        "roi": null,
        "last_updated": "2023-05-07T05:39:33.800Z"
    },
    {
        "id": "dogecoin",
        "symbol": "doge",
        "name": "Dogecoin",
        "image": "https://assets.coingecko.com/coins/images/5/large/dogecoin.png?1547792256",
        "current_price": 0.077041,
        "market_cap": 10717672906,
        "market_cap_rank": 9,
        "fully_diluted_valuation": null,
        "total_volume": 438590236,
        "high_24h": 0.079256,
        "low_24h": 0.076363,
        "price_change_24h": -0.002046213294059907,
        "price_change_percentage_24h": -2.58728,
        "market_cap_change_24h": -304228763.4586849,
        "market_cap_change_percentage_24h": -2.76022,
        "circulating_supply": 139242976383.705,
        "total_supply": null,
        "max_supply": null,
        "ath": 0.731578,
        "ath_change_percentage": -89.4872,
        "ath_date": "2021-05-08T05:08:23.458Z",
        "atl": 8.69e-05,
        "atl_change_percentage": 88399.44834,
        "atl_date": "2015-05-06T00:00:00.000Z",
        "roi": null,
        "last_updated": "2023-05-07T05:39:34.307Z"
    },
    {
        "id": "matic-network",
        "symbol": "matic",
        "name": "Polygon",
        "image": "https://assets.coingecko.com/coins/images/4713/large/matic-token-icon.png?1624446912",
        "current_price": 0.979216,
        "market_cap": 9037672126,
        "market_cap_rank": 10,
        "fully_diluted_valuation": 9771017188,
        "total_volume": 305317003,
        "high_24h": 0.986598,
        "low_24h": 0.953279,
        "price_change_24h": -0.006666211452807437,
        "price_change_percentage_24h": -0.67617,
        "market_cap_change_24h": -82095205.76760292,
        "market_cap_change_percentage_24h": -0.90019,
        "circulating_supply": 9249469069.28493,
        "total_supply": 10000000000.0,
        "max_supply": 10000000000.0,
        "ath": 2.92,
        "ath_change_percentage": -66.53415,
        "ath_date": "2021-12-27T02:08:34.307Z",
        "atl": 0.00314376,
        "atl_change_percentage": 30944.10506,
        "atl_date": "2019-05-10T00:00:00.000Z",
        "roi": {
            "times": 371.32553568823636,
            "currency": "usd",
            "percentage": 37132.553568823634
        },
        "last_updated": "2023-05-07T05:39:33.474Z"
    }
]